osr2mp4/Exceptions.py
osr2mp4/InfoProcessor.py
osr2mp4/__init__.py
osr2mp4/config.json
osr2mp4/global_var.py
osr2mp4/install.py
osr2mp4/osr2mp4.py
osr2mp4/post_install.py
osr2mp4/settings.json
osr2mp4/test.py
osr2mp4/write_data.py
osr2mp4/AudioProcess/AddAudio.py
osr2mp4/AudioProcess/CreateAudio.py
osr2mp4/AudioProcess/Hitsound.py
osr2mp4/AudioProcess/Utils.py
osr2mp4/AudioProcess/__init__.py
osr2mp4/CheckSystem/Health.py
osr2mp4/CheckSystem/HitObjectChecker.py
osr2mp4/CheckSystem/HitresultEnum.py
osr2mp4/CheckSystem/Judgement.py
osr2mp4/CheckSystem/Structs.py
osr2mp4/CheckSystem/__init__.py
osr2mp4/CheckSystem/checkmain.py
osr2mp4/CheckSystem/getgrade.py
osr2mp4/CheckSystem/mathhelper.py
osr2mp4/CheckSystem/HitObjects/HitObject.py
osr2mp4/CheckSystem/HitObjects/Slider.py
osr2mp4/CheckSystem/HitObjects/Spinner.py
osr2mp4/CheckSystem/HitObjects/__init__.py
osr2mp4/EEnum/EAudio.py
osr2mp4/EEnum/EGrade.py
osr2mp4/EEnum/EImageFrom.py
osr2mp4/EEnum/EMods.py
osr2mp4/EEnum/EReplay.py
osr2mp4/EEnum/EState.py
osr2mp4/EEnum/__init__.py
osr2mp4/ImageProcess/__init__.py
osr2mp4/ImageProcess/imageproc.py
osr2mp4/ImageProcess/Animation/__init__.py
osr2mp4/ImageProcess/Animation/alpha.py
osr2mp4/ImageProcess/Animation/easing.py
osr2mp4/ImageProcess/Animation/size.py
osr2mp4/ImageProcess/Curves/__init__.py
osr2mp4/ImageProcess/Curves/abec.py
osr2mp4/ImageProcess/Curves/adjustcurve.py
osr2mp4/ImageProcess/Curves/constants.py
osr2mp4/ImageProcess/Curves/curve2.py
osr2mp4/ImageProcess/Curves/curve3.py
osr2mp4/ImageProcess/Curves/curves.py
osr2mp4/ImageProcess/Curves/curves2.py
osr2mp4/ImageProcess/Curves/generate_slider.py
osr2mp4/ImageProcess/Curves/mathhelper.py
osr2mp4/ImageProcess/Curves/position.py
osr2mp4/ImageProcess/Curves/utils.py
osr2mp4/ImageProcess/Curves/libcurves/Approximator.h
osr2mp4/ImageProcess/Curves/libcurves/BezierApproximator.cpp
osr2mp4/ImageProcess/Curves/libcurves/BezierApproximator.h
osr2mp4/ImageProcess/Curves/libcurves/CMakeLists.txt
osr2mp4-0.0.5.dev4.dist-info/LICENSE
osr2mp4-0.0.5.dev4.dist-info/METADATA
osr2mp4-0.0.5.dev4.dist-info/WHEEL
osr2mp4-0.0.5.dev4.dist-info/top_level.txt
osr2mp4-0.0.5.dev4.dist-info/RECORD
