Metadata-Version: 2.1
Name: osr2mp4
Version: 0.0.5.dev4
Summary: Convert osr replay file to video file
Home-page: https://github.com/uyitroa/osr2mp4-core
Author: yuitora
Author-email: shintaridesu@gmail.com
License: UNKNOWN
Platform: UNKNOWN
Classifier: Programming Language :: Python :: 3
Classifier: License :: OSI Approved :: MIT License
Classifier: Operating System :: OS Independent
Requires-Python: >=3.6
Requires-Dist: oppai
Requires-Dist: pydub
Requires-Dist: numpy
Requires-Dist: opencv-python
Requires-Dist: scipy
Requires-Dist: toolz
Requires-Dist: osrparse
Requires-Dist: recordclass
Requires-Dist: requests
Requires-Dist: autologging
Requires-Dist: configparser
Requires-Dist: cython
